{
  "main": {
    "id": "2667ffe55bb55011",
    "type": "split",
    "children": [
      {
        "id": "4bedac3a871624fd",
        "type": "tabs",
        "children": [
          {
            "id": "6e2dd30b692c33dd",
            "type": "leaf",
            "state": {
              "type": "markdown",
              "state": {
                "file": "Physics/Charge and Field.md",
                "mode": "source",
                "source": false
              },
              "icon": "lucide-file",
              "title": "Charge and Field"
            }
          }
        ]
      }
    ],
    "direction": "vertical"
  },
  "left": {
    "id": "9dca4c9cc25ec8aa",
    "type": "split",
    "children": [
      {
        "id": "8c1a6eb069d96787",
        "type": "tabs",
        "children": [
          {
            "id": "5e0d9e16814e98f0",
            "type": "leaf",
            "state": {
              "type": "file-explorer",
              "state": {
                "sortOrder": "alphabetical",
                "autoReveal": false
              },
              "icon": "lucide-folder-closed",
              "title": "Files"
            }
          },
          {
            "id": "bdd0036b0e1d9cdb",
            "type": "leaf",
            "state": {
              "type": "search",
              "state": {
                "query": "",
                "matchingCase": false,
                "explainSearch": false,
                "collapseAll": false,
                "extraContext": false,
                "sortOrder": "alphabetical"
              },
              "icon": "lucide-search",
              "title": "Search"
            }
          },
          {
            "id": "ff8994f034a42e09",
            "type": "leaf",
            "state": {
              "type": "bookmarks",
              "state": {},
              "icon": "lucide-bookmark",
              "title": "Bookmarks"
            }
          }
        ]
      }
    ],
    "direction": "horizontal",
    "width": 289
  },
  "right": {
    "id": "8372f5363dec9a02",
    "type": "split",
    "children": [
      {
        "id": "a741df4dda6d0e80",
        "type": "tabs",
        "children": [
          {
            "id": "69807210acdc6024",
            "type": "leaf",
            "state": {
              "type": "backlink",
              "state": {
                "file": "Physics/Electromagnetism.md",
                "collapseAll": false,
                "extraContext": false,
                "sortOrder": "alphabetical",
                "showSearch": false,
                "searchQuery": "",
                "backlinkCollapsed": false,
                "unlinkedCollapsed": true
              },
              "icon": "links-coming-in",
              "title": "Backlinks for Electromagnetism"
            }
          },
          {
            "id": "9add529d459ebe5b",
            "type": "leaf",
            "state": {
              "type": "outgoing-link",
              "state": {
                "file": "Physics/Charge and Field.md",
                "linksCollapsed": true,
                "unlinkedCollapsed": true
              },
              "icon": "links-going-out",
              "title": "Outgoing links from Charge and Field"
            }
          },
          {
            "id": "e2fc9b16e2fc68e0",
            "type": "leaf",
            "state": {
              "type": "tag",
              "state": {
                "sortOrder": "frequency",
                "useHierarchy": true,
                "showSearch": false,
                "searchQuery": ""
              },
              "icon": "lucide-tags",
              "title": "Tags"
            }
          },
          {
            "id": "114c9ae34f3c2122",
            "type": "leaf",
            "state": {
              "type": "outline",
              "state": {
                "file": "Physics/Charge and Field.md",
                "followCursor": false,
                "showSearch": false,
                "searchQuery": ""
              },
              "icon": "lucide-list",
              "title": "Outline of Charge and Field"
            }
          },
          {
            "id": "03157bb13870e6d4",
            "type": "leaf",
            "state": {
              "type": "all-properties",
              "state": {
                "sortOrder": "frequency",
                "showSearch": false,
                "searchQuery": ""
              },
              "icon": "lucide-archive",
              "title": "All properties"
            }
          }
        ],
        "currentTab": 1
      }
    ],
    "direction": "horizontal",
    "width": 300,
    "collapsed": true
  },
  "left-ribbon": {
    "hiddenItems": {
      "bases:Create new base": false,
      "switcher:Open quick switcher": false,
      "graph:Open graph view": false,
      "canvas:Create new canvas": false,
      "daily-notes:Open today's daily note": false,
      "templates:Insert template": false,
      "command-palette:Open command palette": false,
      "webpage-html-export:Export Vault to HTML": false
    }
  },
  "active": "6e2dd30b692c33dd",
  "lastOpenFiles": [
    "Physics/Out into Space.md",
    "Physics/Charge and Field.md",
    "Physics/Sensing.md",
    "index.md",
    "Physics/Waves.md",
    "Physics/Simple Models of Matter and Boltzmann Factor.md",
    "Physics/Simple Harmonic Motion.md",
    "Physics/Radioactive Decay and Capacitor Discharge.md",
    "Physics/Quantum.md",
    "Physics/Probing and Ionising.md",
    "Physics/Our Place in the Universe.md",
    "Physics/Materials.md",
    "Physics/Imaging and Signalling.md",
    "Physics/Forces and Motion.md",
    "Physics/Electromagnetism.md",
    "Maths/Statistics/Sampling.md",
    "Maths/Statistics/Probability.md",
    "Maths/Statistics/Distributions and Hypothesis Testing.md",
    "Maths/Pure/Trigonometry.md",
    "Maths/Pure/Sequences and Series.md",
    "Maths/Pure/Pure Year 2 Overview.md",
    "Maths/Pure/Pure Year 1 Overview.md",
    "Maths/Pure/Proof.md",
    "Maths/Pure/Numerical Methods.md",
    "Maths/Pure/Integration.md",
    "Maths/Pure/Functions.md",
    "Maths/Pure",
    "Maths/Statistics",
    "Maths",
    "New folder",
    "Physics/Untitled",
    "Further Maths/Additional Pure",
    "Further Maths/Mechanics",
    "Further Maths/Pure 2",
    "Further Maths/Pure 1",
    "assets/logo.svg",
    "assets/logo.png",
    "Physics",
    "Pasted image 20250529222536.png",
    "logo.svg"
  ]
}